darktable_lut_generator/__init__.py
darktable_lut_generator/estimate_lut.py
darktable_lut_generator/main.py
darktable_lut_generator/make_rgb_image.py
darktable_lut_generator/tryout_highlights.py
darktable_lut_generator/styles/__init__.py
darktable_lut_generator/styles/image.dtstyle
darktable_lut_generator/styles/raw.dtstyle
darktable_lut_generator/styles/raw_lens_correction.dtstyle
darktable_lut_generator-0.1.5.dist-info/LICENSE
darktable_lut_generator-0.1.5.dist-info/METADATA
darktable_lut_generator-0.1.5.dist-info/WHEEL
darktable_lut_generator-0.1.5.dist-info/entry_points.txt
darktable_lut_generator-0.1.5.dist-info/top_level.txt
darktable_lut_generator-0.1.5.dist-info/RECORD
