Metadata-Version: 2.1
Name: darktable-lut-generator
Version: 0.1.5
Summary: Estimate a .cube 3D lookup table from camera images for the Darktable lut 3D module.
Home-page: https://github.com/wilecoyote2015/darktabe_lut_generator
Author: Björn Sonnenschein
Author-email: wilecoyote2015@gmail.com
Project-URL: Bug Tracker, https://github.com/wilecoyote2015/darktabe_lut_generator/issues
Classifier: Programming Language :: Python :: 3
Classifier: License :: OSI Approved :: GNU Lesser General Public License v3 (LGPLv3)
Classifier: Operating System :: OS Independent
Requires-Python: >=3.7
License-File: LICENSE
Requires-Dist: numpy
Requires-Dist: scipy
Requires-Dist: scikit-learn
Requires-Dist: opencv-python
Requires-Dist: tqdm
Requires-Dist: plotly
Requires-Dist: pandas
